json_response.py
django_json_response-1.1.5.dist-info/DESCRIPTION.rst
django_json_response-1.1.5.dist-info/METADATA
django_json_response-1.1.5.dist-info/RECORD
django_json_response-1.1.5.dist-info/WHEEL
django_json_response-1.1.5.dist-info/metadata.json
django_json_response-1.1.5.dist-info/top_level.txt
