Metadata-Version: 2.0
Name: django-json-response
Version: 1.1.5
Summary: DIY Django's JsonResponse and JsonpResponse
Home-page: https://github.com/django-xxx/django-json-response
Author: Hackathon
Author-email: kimi.huang@brightcells.com
License: UNKNOWN
Keywords: django-json-response django-jsonp-response
Platform: UNKNOWN
Classifier: Development Status :: 5 - Production/Stable
Classifier: Environment :: Web Environment
Classifier: Framework :: Django
Classifier: Intended Audience :: Developers
Classifier: Programming Language :: Python
Classifier: Topic :: Software Development :: Libraries :: Python Modules
Classifier: Topic :: Office/Business :: Financial :: Spreadsheet
